pytest_leaks.py
pytest_leaks-0.2.2.dist-info/DESCRIPTION.rst
pytest_leaks-0.2.2.dist-info/METADATA
pytest_leaks-0.2.2.dist-info/RECORD
pytest_leaks-0.2.2.dist-info/WHEEL
pytest_leaks-0.2.2.dist-info/entry_points.txt
pytest_leaks-0.2.2.dist-info/metadata.json
pytest_leaks-0.2.2.dist-info/top_level.txt
