Metadata-Version: 2.0
Name: pytest-leaks
Version: 0.2.2
Summary: A pytest plugin to trace resource leaks.
Home-page: https://github.com/abalkin/pytest-leaks
Author: Alexander Belopolsky
Author-email: alexander.belopolsky@gmail.com
License: MIT
Platform: UNKNOWN
Classifier: Development Status :: 1 - Planning
Classifier: Framework :: Pytest
Classifier: Intended Audience :: Developers
Classifier: Topic :: Software Development :: Testing
Classifier: Programming Language :: Python
Classifier: Programming Language :: Python :: 3.5
Classifier: Programming Language :: Python :: Implementation :: CPython
Classifier: Programming Language :: Python :: Implementation :: PyPy
Classifier: Operating System :: OS Independent
Classifier: License :: OSI Approved :: MIT License
Requires-Dist: pytest (>=2.9.2)
